<resolutions configurationFileName="bs2/configurations/bs2.xml" totalWckTime="1199833">
<resolution>
<instance framework="CSP" name="ProblemFile-Bibd-sc-34-085-30-12-10_c18"/>
<domains nTypes="1" nValues="101150" sizes="[2#50575]"/>
<variables count="50575" degrees="[2#47685,37#4,38#230,39#2656]"/>
<constraints arities="[3#47685,34#85,68#84,85#595,170#33]" count="48482" cpu="8.078" distribution="[CtrIntension#47685,LexicographicLE#117,SumSimpleEQ#680]" mem="3416M453" nIntStructures="(1,shared:47684)" nSpecific="797" wck="6.461"/>
<solver cpu="10.13" guaranteedGAC="true" mem="10069M965" wck="13.386">
<preprocessing ccks="333729" cpu="10.336" filters="0" inconsistency="false" mem="10069M965" nACremovedValues="0" nTotalRemovedValues="0" revisions="(143055,useless=143055)" wck="0.177"/>
<run backtracks="14" ccks="354595" decisions="142" depth="100..110" failedAssignments="10" filters="5369" mem="10104M43" nogoods="1" num="0" revisions="(169954,useless=164806)" wck="0.694" wrong="21"/>
<run backtracks="18" ccks="441611" decisions="249" depth="1..87" failedAssignments="21" filters="33303" mem="10104M43" nogoods="11" num="1" revisions="(245640,useless=213434)" wck="1.092" wrong="36"/>
<run backtracks="20" ccks="482335" decisions="366" depth="1..100" failedAssignments="33" filters="45604" mem="10104M43" nogoods="22" num="2" revisions="(283794,useless=239551)" wck="1.384" wrong="50"/>
<run backtracks="22" ccks="558737" decisions="546" depth="1..162" failedAssignments="46" filters="72464" mem="10104M43" nogoods="34" num="3" revisions="(367085,useless=296716)" wck="1.865" wrong="65"/>
<run backtracks="26" ccks="634780" decisions="697" depth="1..128" failedAssignments="60" filters="104594" mem="10104M43" nogoods="45" num="4" revisions="(463451,useless=361745)" wck="2.333" wrong="82"/>
<run backtracks="26" ccks="709997" decisions="908" depth="1..194" failedAssignments="76" filters="135985" mem="10104M43" nogoods="61" num="5" revisions="(555194,useless=422810)" wck="2.889" wrong="98"/>
<run backtracks="37" ccks="769620" decisions="1131" depth="1..202" failedAssignments="93" filters="160079" mem="10104M43" nogoods="68" num="6" revisions="(629149,useless=473286)" wck="3.436" wrong="116"/>
<run backtracks="63" ccks="820236" decisions="1369" depth="1..184" failedAssignments="112" filters="179657" mem="10104M43" nogoods="75" num="7" revisions="(693029,useless=518045)" wck="3.967" wrong="148"/>
<run backtracks="95" ccks="864910" decisions="1543" depth="1..109" failedAssignments="133" filters="195275" mem="10104M43" nogoods="82" num="8" revisions="(741907,useless=551647)" wck="4.335" wrong="186"/>
<run backtracks="127" ccks="904305" decisions="1768" depth="1..165" failedAssignments="156" filters="209118" mem="10104M43" nogoods="86" num="9" revisions="(794305,useless=590502)" wck="4.814" wrong="222"/>
<run backtracks="147" ccks="1032269" decisions="2115" depth="1..272" failedAssignments="181" filters="259699" mem="10104M43" nogoods="93" num="10" revisions="(932149,useless=679012)" wck="5.497" wrong="263"/>
<run backtracks="204" ccks="1111053" decisions="2672" depth="1..438" failedAssignments="209" filters="288458" mem="10104M43" nogoods="104" num="11" revisions="(1032645,useless=751320)" wck="6.456" wrong="331"/>
<run backtracks="232" ccks="1150942" decisions="2911" depth="1..168" failedAssignments="240" filters="303507" mem="10104M43" nogoods="108" num="12" revisions="(1097738,useless=801994)" wck="6.848" wrong="382"/>
<run backtracks="283" ccks="1207806" decisions="3195" depth="1..173" failedAssignments="274" filters="322607" mem="10104M43" nogoods="115" num="13" revisions="(1172605,useless=858359)" wck="7.334" wrong="446"/>
<run backtracks="366" ccks="1285039" decisions="3549" depth="2..154" failedAssignments="311" filters="352583" mem="10104M43" nogoods="121" num="14" revisions="(1324609,useless=981261)" wck="7.93" wrong="555"/>
<run backtracks="402" ccks="1355888" decisions="3837" depth="2..144" failedAssignments="352" filters="380769" mem="10104M43" nogoods="128" num="15" revisions="(1434217,useless=1063924)" wck="8.376" wrong="630"/>
<run backtracks="496" ccks="1412510" decisions="4217" depth="3..192" failedAssignments="397" filters="399137" mem="10104M43" nogoods="132" num="16" revisions="(1501360,useless=1113029)" wck="9.069" wrong="728"/>
<run backtracks="578" ccks="1475036" decisions="4585" depth="8..172" failedAssignments="447" filters="419912" mem="10104M43" nogoods="139" num="17" revisions="(1590534,useless=1182065)" wck="9.707" wrong="833"/>
<run backtracks="670" ccks="1559159" decisions="4992" depth="8..179" failedAssignments="502" filters="451219" mem="10104M43" nogoods="148" num="18" revisions="(1696638,useless=1257876)" wck="10.441" wrong="955"/>
<run backtracks="931" ccks="1651637" decisions="5651" depth="9..173" failedAssignments="563" filters="475720" mem="10104M43" nogoods="151" num="19" revisions="(1911106,useless=1448599)" wck="11.402" wrong="1219"/>
<run backtracks="1051" ccks="1723906" decisions="6039" depth="8..152" failedAssignments="630" filters="498586" mem="10104M43" nogoods="153" num="20" revisions="(1990250,useless=1505290)" wck="12.06" wrong="1345"/>
<run backtracks="1220" ccks="1987679" decisions="6517" depth="8..147" failedAssignments="704" filters="618104" mem="10104M43" nogoods="159" num="21" revisions="(2428927,useless=1827465)" wck="13.145" wrong="1519"/>
<run backtracks="1349" ccks="2146873" decisions="6975" depth="12..156" failedAssignments="785" filters="688171" mem="10104M43" nogoods="173" num="22" revisions="(2676130,useless=2006853)" wck="13.965" wrong="1680"/>
<run backtracks="1463" ccks="2214086" decisions="7442" depth="110..167" failedAssignments="874" filters="710216" mem="10104M43" nogoods="175" num="23" revisions="(2761937,useless=2071409)" wck="14.641" wrong="1849"/>
<run backtracks="1576" ccks="2291735" decisions="7892" depth="24..155" failedAssignments="972" filters="738375" mem="10104M43" nogoods="195" num="24" revisions="(2938700,useless=2221691)" wck="15.381" wrong="2011"/>
<run backtracks="1909" ccks="2413036" decisions="8686" depth="110..135" failedAssignments="1080" filters="790322" mem="10104M43" nogoods="200" num="25" revisions="(3400647,useless=2636154)" wck="16.622" wrong="2350"/>
<run backtracks="2184" ccks="2583347" decisions="9426" depth="10..157" failedAssignments="1199" filters="845890" mem="10104M43" nogoods="217" num="26" revisions="(3685450,useless=2867272)" wck="17.809" wrong="2657"/>
<run backtracks="2415" ccks="2775344" decisions="10166" depth="15..248" failedAssignments="1330" filters="908421" mem="10104M43" nogoods="230" num="27" revisions="(3906414,useless=3027198)" wck="19.036" wrong="2913"/>
<run backtracks="2720" ccks="2958021" decisions="10959" depth="15..172" failedAssignments="1474" filters="962242" mem="10104M43" nogoods="243" num="28" revisions="(4167610,useless=3236253)" wck="20.237" wrong="3233"/>
<run backtracks="2964" ccks="3124568" decisions="11691" depth="9..169" failedAssignments="1632" filters="1015810" mem="10104M43" nogoods="257" num="29" revisions="(4415050,useless=3432179)" wck="21.288" wrong="3533"/>
<run backtracks="3290" ccks="3449247" decisions="12734" depth="23..159" failedAssignments="1806" filters="1147412" mem="10104M43" nogoods="269" num="30" revisions="(4954823,useless=3846465)" wck="22.96" wrong="3982"/>
<run backtracks="3736" ccks="3805656" decisions="13922" depth="0..160" failedAssignments="1997" filters="1276495" mem="10104M43" nogoods="281" num="31" revisions="(5360567,useless=4127818)" wck="24.63" wrong="4508"/>
<run backtracks="4108" ccks="3985197" decisions="15004" depth="19..322" failedAssignments="2208" filters="1324425" mem="10104M43" nogoods="297" num="32" revisions="(5594509,useless=4315073)" wck="26.315" wrong="4899"/>
<run backtracks="4739" ccks="4283066" decisions="16495" depth="31..151" failedAssignments="2440" filters="1426014" mem="10104M43" nogoods="309" num="33" revisions="(6040900,useless=4663786)" wck="28.555" wrong="5578"/>
<run backtracks="5307" ccks="4897483" decisions="17956" depth="19..159" failedAssignments="2695" filters="1647904" mem="10104M43" nogoods="319" num="34" revisions="(6910919,useless=5318684)" wck="30.768" wrong="6251"/>
<run backtracks="5639" ccks="5601762" decisions="19239" depth="22..128" failedAssignments="2976" filters="1935470" mem="10104M43" nogoods="324" num="35" revisions="(7773763,useless=5902648)" wck="32.77" wrong="6843"/>
<run backtracks="6053" ccks="7829619" decisions="20606" depth="0..85" failedAssignments="3285" filters="2980054" mem="10104M43" nogoods="329" num="36" revisions="(10520883,useless=7631327)" wck="36.575" wrong="7518"/>
<run backtracks="6792" ccks="8609014" decisions="22596" depth="0..390" failedAssignments="3625" filters="3303135" mem="10104M43" nogoods="340" num="37" revisions="(11673906,useless=8467475)" wck="40.092" wrong="8328"/>
<run backtracks="7513" ccks="8952390" decisions="24602" depth="3..422" failedAssignments="3999" filters="3401063" mem="10104M43" nogoods="356" num="38" revisions="(12075971,useless=8774167)" wck="42.839" wrong="9141"/>
<run backtracks="8400" ccks="9312561" decisions="26725" depth="3..193" failedAssignments="4410" filters="3531682" mem="10104M43" nogoods="373" num="39" revisions="(13116843,useless=9693161)" wck="45.752" wrong="10118"/>
<run backtracks="9389" ccks="10062232" decisions="29287" depth="2..171" failedAssignments="4862" filters="3771472" mem="10104M43" nogoods="385" num="40" revisions="(13906769,useless=10252289)" wck="48.747" wrong="11319"/>
<run backtracks="10690" ccks="10611099" decisions="32259" depth="2..183" failedAssignments="5359" filters="3961961" mem="10104M43" nogoods="396" num="41" revisions="(15273073,useless=11439817)" wck="52.721" wrong="12727"/>
<run backtracks="11614" ccks="11032633" decisions="34868" depth="10..420" failedAssignments="5906" filters="4069258" mem="10104M43" nogoods="413" num="42" revisions="(15950590,useless=12013843)" wck="55.967" wrong="13858"/>
<run backtracks="12859" ccks="11560118" decisions="37765" depth="2..309" failedAssignments="6508" filters="4214002" mem="10104M43" nogoods="425" num="43" revisions="(16804693,useless=12728524)" wck="59.474" wrong="15164"/>
<run backtracks="15097" ccks="12268110" decisions="42421" depth="1..173" failedAssignments="7170" filters="4379591" mem="10104M43" nogoods="439" num="44" revisions="(17808837,useless=13573801)" wck="64.629" wrong="17440"/>
<run backtracks="16932" ccks="12824617" decisions="46285" depth="1..93" failedAssignments="7898" filters="4528634" mem="10104M43" nogoods="447" num="45" revisions="(18499894,useless=14124198)" wck="68.682" wrong="19336"/>
<run backtracks="18875" ccks="14021520" decisions="50728" depth="1..364" failedAssignments="8699" filters="4926459" mem="10104M43" nogoods="464" num="46" revisions="(19950294,useless=15184044)" wck="74.522" wrong="21393"/>
<run backtracks="20566" ccks="14771333" decisions="54890" depth="1..174" failedAssignments="9580" filters="5173871" mem="10104M43" nogoods="478" num="47" revisions="(21003592,useless=16000653)" wck="78.596" wrong="23397"/>
<run backtracks="22413" ccks="15571875" decisions="58910" depth="1..151" failedAssignments="10550" filters="5418857" mem="10104M43" nogoods="489" num="48" revisions="(21897069,useless=16658674)" wck="82.444" wrong="25346"/>
<run backtracks="24761" ccks="16527821" decisions="64259" depth="1..389" failedAssignments="11617" filters="5710689" mem="10104M43" nogoods="507" num="49" revisions="(23671580,useless=18152426)" wck="88.125" wrong="27850"/>
<run backtracks="26938" ccks="17724910" decisions="69488" depth="1..291" failedAssignments="12790" filters="6092274" mem="10104M43" nogoods="530" num="50" revisions="(25106757,useless=19219744)" wck="93.526" wrong="30344"/>
<run backtracks="29771" ccks="19046514" decisions="75791" depth="1..250" failedAssignments="14081" filters="6471087" mem="10104M43" nogoods="550" num="51" revisions="(26767625,useless=20513132)" wck="99.903" wrong="33384"/>
<run backtracks="31477" ccks="20537632" decisions="82000" depth="2..148" failedAssignments="15501" filters="7003039" mem="10104M43" nogoods="557" num="52" revisions="(28340397,useless=21573181)" wck="104.515" wrong="36450"/>
<run backtracks="34413" ccks="21646380" decisions="89004" depth="0..253" failedAssignments="17063" filters="7282723" mem="10104M43" nogoods="566" num="53" revisions="(29755909,useless=22722097)" wck="111.065" wrong="39872"/>
<run backtracks="37164" ccks="24414408" decisions="96643" depth="3..239" failedAssignments="18781" filters="8162000" mem="10104M43" nogoods="583" num="54" revisions="(32877624,useless=24997120)" wck="119.08" wrong="43602"/>
<run backtracks="41032" ccks="25719713" decisions="104707" depth="4..164" failedAssignments="20671" filters="8437150" mem="10104M43" nogoods="596" num="55" revisions="(34573971,useless=26427710)" wck="127.16" wrong="47582"/>
<run backtracks="45144" ccks="27778643" decisions="114261" depth="1..245" failedAssignments="22750" filters="9036860" mem="10104M43" nogoods="618" num="56" revisions="(36998604,useless=28269228)" wck="137.432" wrong="52251"/>
<run backtracks="49332" ccks="30260775" decisions="126007" depth="1..175" failedAssignments="25037" filters="9919936" mem="10104M43" nogoods="631" num="57" revisions="(40588531,useless=31017532)" wck="149.098" wrong="58067"/>
<run backtracks="54590" ccks="32222507" decisions="137082" depth="1..262" failedAssignments="27553" filters="10391817" mem="10104M43" nogoods="649" num="58" revisions="(43507910,useless=33479870)" wck="160.718" wrong="63512"/>
<run backtracks="60252" ccks="35588885" decisions="150395" depth="14..275" failedAssignments="30321" filters="11493156" mem="10104M43" nogoods="668" num="59" revisions="(48118408,useless=37019321)" wck="175.023" wrong="70051"/>
<run backtracks="68419" ccks="41931606" decisions="168083" depth="17..448" failedAssignments="33365" filters="13849777" mem="10104M43" nogoods="697" num="60" revisions="(55998606,useless=42610987)" wck="195.839" wrong="78691"/>
<run backtracks="76101" ccks="47704003" decisions="183935" depth="12..199" failedAssignments="36714" filters="16108313" mem="10104M43" nogoods="718" num="61" revisions="(62905437,useless=47325146)" wck="214.797" wrong="86531"/>
<run backtracks="83312" ccks="49899606" decisions="198844" depth="12..188" failedAssignments="40398" filters="16567181" mem="10104M43" nogoods="734" num="62" revisions="(67010130,useless=50989667)" wck="229.437" wrong="93906"/>
<run backtracks="92939" ccks="52713882" decisions="219083" depth="37..185" failedAssignments="44450" filters="17322260" mem="10104M43" nogoods="743" num="63" revisions="(70472970,useless=53747578)" wck="247.835" wrong="103954"/>
<run backtracks="102168" ccks="56709536" decisions="238890" depth="7..110" failedAssignments="48907" filters="18912035" mem="10104M43" nogoods="753" num="64" revisions="(81983592,useless=63778225)" wck="268.533" wrong="113834"/>
<run backtracks="110800" ccks="66900581" decisions="259021" depth="0..86" failedAssignments="53810" filters="23263940" mem="10104M43" nogoods="763" num="65" revisions="(95575332,useless=73172960)" wck="293.267" wrong="123866"/>
<run backtracks="122925" ccks="74484750" decisions="285438" depth="49..314" failedAssignments="59204" filters="25860507" mem="10104M43" nogoods="780" num="66" revisions="(105159676,useless=80207779)" wck="323.135" wrong="136941"/>
<run backtracks="136543" ccks="89190824" decisions="313382" depth="49..69" failedAssignments="65137" filters="32389394" mem="10104M43" nogoods="789" num="67" revisions="(133985590,useless=102723616)" wck="363.711" wrong="150885"/>
<run backtracks="150205" ccks="101921721" decisions="342356" depth="48..316" failedAssignments="71663" filters="37944840" mem="10104M43" nogoods="814" num="68" revisions="(154111690,useless=117495626)" wck="401.048" wrong="165233"/>
<run backtracks="164244" ccks="107076719" decisions="371924" depth="11..320" failedAssignments="78842" filters="39220201" mem="10104M43" nogoods="828" num="69" revisions="(160058061,useless=122210380)" wck="436.574" wrong="179866"/>
<run backtracks="178079" ccks="112340589" decisions="400817" depth="23..268" failedAssignments="86739" filters="40534565" mem="10104M43" nogoods="843" num="70" revisions="(167861758,useless=128754223)" wck="464.905" wrong="194204"/>
<run backtracks="199896" ccks="118614389" decisions="445257" depth="27..206" failedAssignments="95426" filters="41784679" mem="10104M43" nogoods="852" num="71" revisions="(178134384,useless=137826575)" wck="507.086" wrong="216336"/>
<run backtracks="222125" ccks="127863672" decisions="491612" depth="44..452" failedAssignments="104981" filters="44374989" mem="10104M43" nogoods="874" num="72" revisions="(192616564,useless=149795061)" wck="555.096" wrong="239306"/>
<run backtracks="244097" ccks="135386007" decisions="538237" depth="90..316" failedAssignments="115492" filters="46089173" mem="10104M43" nogoods="893" num="73" revisions="(205231538,useless=160767982)" wck="599.516" wrong="262484"/>
<run backtracks="270546" ccks="146316116" decisions="594714" depth="65..194" failedAssignments="127054" filters="50119497" mem="10104M43" nogoods="906" num="74" revisions="(229996159,useless=181725505)" wck="660.43" wrong="290635"/>
<run backtracks="304749" ccks="161269984" decisions="666820" depth="94..182" failedAssignments="139772" filters="54786776" mem="10104M43" nogoods="918" num="75" revisions="(253708401,useless=200951263)" wck="740.391" wrong="326611"/>
<run backtracks="345577" ccks="186077351" decisions="752230" depth="72..447" failedAssignments="153762" filters="63773551" mem="10104M43" nogoods="939" num="76" revisions="(299020850,useless=237562587)" wck="837.098" wrong="369110"/>
<run backtracks="376068" ccks="197301615" decisions="825036" depth="1..319" failedAssignments="169151" filters="66609349" mem="10104M43" nogoods="965" num="77" revisions="(312149955,useless=247977265)" wck="899.565" wrong="405373"/>
<run backtracks="410992" ccks="207701254" decisions="896109" depth="1..196" failedAssignments="186079" filters="68777163" mem="10104M43" nogoods="980" num="78" revisions="(330528126,useless=264273423)" wck="968.132" wrong="440840"/>
<run backtracks="447209" ccks="222052355" decisions="971122" depth="23..154" failedAssignments="204700" filters="72705572" mem="10104M43" nogoods="992" num="79" revisions="(350023884,useless=280017114)" wck="1045.381" wrong="478294"/>
<run backtracks="492052" ccks="236889642" decisions="1061540" depth="90..120" failedAssignments="225184" filters="75803186" mem="10104M43" nogoods="1000" num="80" revisions="(387533971,useless=314536047)" wck="1137.064" wrong="523455"/>
<run backtracks="514416" ccks="247619950" decisions="1109129" depth="19..309" failedAssignments="236525" filters="79044408" mem="10104M43" nogoods="1000" num="81" revisions="(399928432,useless=323758460)" wck="1186.598" wrong="547119"/>
<global Stop="EXCEEDED_TIME" ccks="247619950" cpu="1196.663" filters="79044408" mem="10104M43" nogoods="1000" revisions="(399928432,useless=323758460)" wck="1200.006" wrong="547119"/>
</solver>
</resolution>
</resolutions>
